README.md
setup.py
confidentify_client/__init__.py
confidentify_client/api_client.py
confidentify_client/configuration.py
confidentify_client/exceptions.py
confidentify_client/rest.py
confidentify_client_python.egg-info/PKG-INFO
confidentify_client_python.egg-info/SOURCES.txt
confidentify_client_python.egg-info/dependency_links.txt
confidentify_client_python.egg-info/requires.txt
confidentify_client_python.egg-info/top_level.txt