Metadata-Version: 1.0
Name: confidentify-client-python
Version: 1.5.0
Summary: Confidentify Client for Python
Home-page: https://confidentify.com
Author: Confidentify
Author-email: info@confidentify.com
License: UNKNOWN
Keywords: Confidentify,API
Platform: UNKNOWN
